ghostmark/__main__.py
ghostmark/image_hashing.py
ghostmark/metadata_parser.py
ghostmark/metadata_scrubber.py
ghostmark/msg_embed.py
ghostmark/nvm.py
ghostmark/password_protection_detection.py
ghostmark/steganography_detection.py
ghostmark/text_extraction.py
ghostmark-1.0.0.dist-info/licenses/LICENSE
ghostmark-1.0.0.dist-info/METADATA
ghostmark-1.0.0.dist-info/WHEEL
ghostmark-1.0.0.dist-info/entry_points.txt
ghostmark-1.0.0.dist-info/top_level.txt
ghostmark-1.0.0.dist-info/RECORD
