Metadata-Version: 2.4
Name: ghostmark
Version: 1.0.0
Summary: Offline CLI toolkit for image metadata, steganography, hidden data detection, and image hashing.
Author-email: Bhavika Nagdeo <bhavikanagdeo83@gmail.com>, Ranveer Kohli <bugatsec@gmail.com>
License: MIT License
Project-URL: Homepage, https://github.com/cracking-bytes/Ghostmark
Project-URL: GitHub Repository, https://github.com/cracking-bytes/Ghostmark
Keywords: image,steganography,metadata,image-forensics,hashing,CLI
Classifier: Programming Language :: Python :: 3
Classifier: License :: OSI Approved :: MIT License
Classifier: Operating System :: OS Independent
License-File: LICENSE
Requires-Dist: Pillow
Requires-Dist: piexif
Requires-Dist: imagehash
Requires-Dist: numpy
Requires-Dist: py7zr
Dynamic: license-file
